setup.py
railgun/__init__.py
railgun/_helper.py
railgun/cdata.py
railgun/cfuncs.py
railgun/cmemsubsets.py
railgun/simobj.py
railgun.egg-info/PKG-INFO
railgun.egg-info/SOURCES.txt
railgun.egg-info/dependency_links.txt
railgun.egg-info/top_level.txt
src/cstylemodule.c