Metadata-Version: 1.0
Name: railgun
Version: 0.1.6
Summary: ctypes utilities for faster and easier simulation programming in C and Python
Home-page: http://bitbucket.org/tkf/railgun/src
Author: Takafumi Arakaki
Author-email: aka.tkf@gmail.com
License: MIT License
Keywords: numerical simulation,research,ctypes,numpy,c
Platform: UNKNOWN
Classifier: Development Status :: 3 - Alpha
Classifier: Intended Audience :: Science/Research
Classifier: Intended Audience :: Developers
Classifier: Operating System :: POSIX :: Linux
Classifier: License :: OSI Approved :: MIT License
Classifier: Programming Language :: Python
Classifier: Topic :: Scientific/Engineering
